[
	{
		"geoName": "Italy",
		"domainNo": 1,
		"geoCode": "IT",
		"geoCodeId": "039000000000",
		"geoCountryId": "IT"
	},
	{
		"geoName": "Agriento",
		"domainNo": 1,
		"geoStateId": "AG",
		"geoCode": "AG",
		"geoCodeId": "039001000000",
		"geoCountryId": "IT"
	},
	{
		"geoName": "Alessandria",
		"domainNo": 1,
		"geoStateId": "AL",
		"geoCode": "AL",
		"geoCodeId": "039002000000",
		"geoCountryId": "IT"
	},
	{
		"geoName": "Ancona",
		"domainNo": 1,
		"geoStateId": "AN",
		"geoCode": "AN",
		"geoCodeId": "039003000000",
		"geoCountryId": "IT"
	},
	{
		"geoName": "Valle d'Aosta",
		"domainNo": 1,
		"geoStateId": "AO",
		"geoCode": "AO",
		"geoCodeId": "039004000000",
		"geoCountryId": "IT"
	},
	{
		"geoName": "Ascoli Piceno",
		"domainNo": 1,
		"geoStateId": "AP",
		"geoCode": "AP",
		"geoCodeId": "039005000000",
		"geoCountryId": "IT"
	},
	{
		"geoName": "L'Aquila",
		"domainNo": 1,
		"geoStateId": "AQ",
		"geoCode": "AQ",
		"geoCodeId": "039006000000",
		"geoCountryId": "IT"
	},
	{
		"geoName": "Arezzo",
		"domainNo": 1,
		"geoStateId": "AR",
		"geoCode": "AR",
		"geoCodeId": "039007000000",
		"geoCountryId": "IT"
	},
	{
		"geoName": "Asti",
		"domainNo": 1,
		"geoStateId": "AT",
		"geoCode": "AT",
		"geoCodeId": "039008000000",
		"geoCountryId": "IT"
	},
	{
		"geoName": "Avellino",
		"domainNo": 1,
		"geoStateId": "AV",
		"geoCode": "AV",
		"geoCodeId": "039009000000",
		"geoCountryId": "IT"
	},
	{
		"geoName": "Bari",
		"domainNo": 1,
		"geoStateId": "BA",
		"geoCode": "BA",
		"geoCodeId": "039010000000",
		"geoCountryId": "IT"
	},
	{
		"geoName": "Bergamo",
		"domainNo": 1,
		"geoStateId": "BG",
		"geoCode": "BG",
		"geoCodeId": "039011000000",
		"geoCountryId": "IT"
	},
	{
		"geoName": "Biella",
		"domainNo": 1,
		"geoStateId": "BI",
		"geoCode": "BI",
		"geoCodeId": "039012000000",
		"geoCountryId": "IT"
	},
	{
		"geoName": "Belluno",
		"domainNo": 1,
		"geoStateId": "BL",
		"geoCode": "BL",
		"geoCodeId": "039013000000",
		"geoCountryId": "IT"
	},
	{
		"geoName": "Benevento",
		"domainNo": 1,
		"geoStateId": "BN",
		"geoCode": "BN",
		"geoCodeId": "039014000000",
		"geoCountryId": "IT"
	},
	{
		"geoName": "Bologna",
		"domainNo": 1,
		"geoStateId": "BO",
		"geoCode": "BO",
		"geoCodeId": "039015000000",
		"geoCountryId": "IT"
	},
	{
		"geoName": "Brindisi",
		"domainNo": 1,
		"geoStateId": "BR",
		"geoCode": "BR",
		"geoCodeId": "039016000000",
		"geoCountryId": "IT"
	},
	{
		"geoName": "Brescia",
		"domainNo": 1,
		"geoStateId": "BS",
		"geoCode": "BS",
		"geoCodeId": "039017000000",
		"geoCountryId": "IT"
	},
	{
		"geoName": "Barletta-Andr.-Trani",
		"domainNo": 1,
		"geoStateId": "BT",
		"geoCode": "BT",
		"geoCodeId": "039018000000",
		"geoCountryId": "IT"
	},
	{
		"geoName": "Bolzano",
		"domainNo": 1,
		"geoStateId": "BZ",
		"geoCode": "BZ",
		"geoCodeId": "039019000000",
		"geoCountryId": "IT"
	},
	{
		"geoName": "Cagliari",
		"domainNo": 1,
		"geoStateId": "CA",
		"geoCode": "CA",
		"geoCodeId": "039020000000",
		"geoCountryId": "IT"
	},
	{
		"geoName": "Campobasso",
		"domainNo": 1,
		"geoStateId": "CB",
		"geoCode": "CB",
		"geoCodeId": "039021000000",
		"geoCountryId": "IT"
	},
	{
		"geoName": "Caserta",
		"domainNo": 1,
		"geoStateId": "CE",
		"geoCode": "CE",
		"geoCodeId": "039022000000",
		"geoCountryId": "IT"
	},
	{
		"geoName": "Chieti",
		"domainNo": 1,
		"geoStateId": "CH",
		"geoCode": "CH",
		"geoCodeId": "039023000000",
		"geoCountryId": "IT"
	},
	{
		"geoName": "Carbonia-Iglesias",
		"domainNo": 1,
		"geoStateId": "CI",
		"geoCode": "CI",
		"geoCodeId": "039024000000",
		"geoCountryId": "IT"
	},
	{
		"geoName": "Caltanisetta",
		"domainNo": 1,
		"geoStateId": "CL",
		"geoCode": "CL",
		"geoCodeId": "039025000000",
		"geoCountryId": "IT"
	},
	{
		"geoName": "Cuneo",
		"domainNo": 1,
		"geoStateId": "CN",
		"geoCode": "CN",
		"geoCodeId": "039026000000",
		"geoCountryId": "IT"
	},
	{
		"geoName": "Como",
		"domainNo": 1,
		"geoStateId": "CO",
		"geoCode": "CO",
		"geoCodeId": "039027000000",
		"geoCountryId": "IT"
	},
	{
		"geoName": "Cremona",
		"domainNo": 1,
		"geoStateId": "CR",
		"geoCode": "CR",
		"geoCodeId": "039028000000",
		"geoCountryId": "IT"
	},
	{
		"geoName": "Cosenza",
		"domainNo": 1,
		"geoStateId": "CS",
		"geoCode": "CS",
		"geoCodeId": "039029000000",
		"geoCountryId": "IT"
	},
	{
		"geoName": "Catania",
		"domainNo": 1,
		"geoStateId": "CT",
		"geoCode": "CT",
		"geoCodeId": "039030000000",
		"geoCountryId": "IT"
	},
	{
		"geoName": "Catanzaro",
		"domainNo": 1,
		"geoStateId": "CZ",
		"geoCode": "CZ",
		"geoCodeId": "039031000000",
		"geoCountryId": "IT"
	},
	{
		"geoName": "Enna",
		"domainNo": 1,
		"geoStateId": "EN",
		"geoCode": "EN",
		"geoCodeId": "039032000000",
		"geoCountryId": "IT"
	},
	{
		"geoName": "Forli/Cesana",
		"domainNo": 1,
		"geoStateId": "FC",
		"geoCode": "FC",
		"geoCodeId": "039033000000",
		"geoCountryId": "IT"
	},
	{
		"geoName": "Ferrara",
		"domainNo": 1,
		"geoStateId": "FE",
		"geoCode": "FE",
		"geoCodeId": "039034000000",
		"geoCountryId": "IT"
	},
	{
		"geoName": "Foggia",
		"domainNo": 1,
		"geoStateId": "FG",
		"geoCode": "FG",
		"geoCodeId": "039035000000",
		"geoCountryId": "IT"
	},
	{
		"geoName": "Firenze",
		"domainNo": 1,
		"geoStateId": "FI",
		"geoCode": "FI",
		"geoCodeId": "039036000000",
		"geoCountryId": "IT"
	},
	{
		"geoName": "Fermo",
		"domainNo": 1,
		"geoStateId": "FM",
		"geoCode": "FM",
		"geoCodeId": "039037000000",
		"geoCountryId": "IT"
	},
	{
		"geoName": "Frosinone",
		"domainNo": 1,
		"geoStateId": "FR",
		"geoCode": "FR",
		"geoCodeId": "039038000000",
		"geoCountryId": "IT"
	},
	{
		"geoName": "Genova",
		"domainNo": 1,
		"geoStateId": "GE",
		"geoCode": "GE",
		"geoCodeId": "039039000000",
		"geoCountryId": "IT"
	},
	{
		"geoName": "Gorizia",
		"domainNo": 1,
		"geoStateId": "GO",
		"geoCode": "GO",
		"geoCodeId": "039040000000",
		"geoCountryId": "IT"
	},
	{
		"geoName": "Grosseto",
		"domainNo": 1,
		"geoStateId": "GR",
		"geoCode": "GR",
		"geoCodeId": "039041000000",
		"geoCountryId": "IT"
	},
	{
		"geoName": "Imperia",
		"domainNo": 1,
		"geoStateId": "IM",
		"geoCode": "IM",
		"geoCodeId": "039042000000",
		"geoCountryId": "IT"
	},
	{
		"geoName": "Isernia",
		"domainNo": 1,
		"geoStateId": "IS",
		"geoCode": "IS",
		"geoCodeId": "039043000000",
		"geoCountryId": "IT"
	},
	{
		"geoName": "Italy",
		"domainNo": 1,
		"geoStateId": "IT",
		"geoCode": "IT",
		"geoCodeId": "039044000000",
		"geoCountryId": "IT"
	},
	{
		"geoName": "Crotone",
		"domainNo": 1,
		"geoStateId": "KR",
		"geoCode": "KR",
		"geoCodeId": "039045000000",
		"geoCountryId": "IT"
	},
	{
		"geoName": "Lecco",
		"domainNo": 1,
		"geoStateId": "LC",
		"geoCode": "LC",
		"geoCodeId": "039046000000",
		"geoCountryId": "IT"
	},
	{
		"geoName": "Lecce",
		"domainNo": 1,
		"geoStateId": "LE",
		"geoCode": "LE",
		"geoCodeId": "039047000000",
		"geoCountryId": "IT"
	},
	{
		"geoName": "Livorno",
		"domainNo": 1,
		"geoStateId": "LI",
		"geoCode": "LI",
		"geoCodeId": "039048000000",
		"geoCountryId": "IT"
	},
	{
		"geoName": "Lodi",
		"domainNo": 1,
		"geoStateId": "LO",
		"geoCode": "LO",
		"geoCodeId": "039049000000",
		"geoCountryId": "IT"
	},
	{
		"geoName": "Latina",
		"domainNo": 1,
		"geoStateId": "LT",
		"geoCode": "LT",
		"geoCodeId": "039050000000",
		"geoCountryId": "IT"
	},
	{
		"geoName": "Lucca",
		"domainNo": 1,
		"geoStateId": "LU",
		"geoCode": "LU",
		"geoCodeId": "039051000000",
		"geoCountryId": "IT"
	},
	{
		"geoName": "Monza Brianza",
		"domainNo": 1,
		"geoStateId": "MB",
		"geoCode": "MB",
		"geoCodeId": "039052000000",
		"geoCountryId": "IT"
	},
	{
		"geoName": "Macerata",
		"domainNo": 1,
		"geoStateId": "MC",
		"geoCode": "MC",
		"geoCodeId": "039053000000",
		"geoCountryId": "IT"
	},
	{
		"geoName": "Messina",
		"domainNo": 1,
		"geoStateId": "ME",
		"geoCode": "ME",
		"geoCodeId": "039054000000",
		"geoCountryId": "IT"
	},
	{
		"geoName": "Milano",
		"domainNo": 1,
		"geoStateId": "MI",
		"geoCode": "MI",
		"geoCodeId": "039055000000",
		"geoCountryId": "IT"
	},
	{
		"geoName": "Mantova",
		"domainNo": 1,
		"geoStateId": "MN",
		"geoCode": "MN",
		"geoCodeId": "039056000000",
		"geoCountryId": "IT"
	},
	{
		"geoName": "Modena",
		"domainNo": 1,
		"geoStateId": "MO",
		"geoCode": "MO",
		"geoCodeId": "039057000000",
		"geoCountryId": "IT"
	},
	{
		"geoName": "Massa Carrara",
		"domainNo": 1,
		"geoStateId": "MS",
		"geoCode": "MS",
		"geoCodeId": "039058000000",
		"geoCountryId": "IT"
	},
	{
		"geoName": "Matera",
		"domainNo": 1,
		"geoStateId": "MT",
		"geoCode": "MT",
		"geoCodeId": "039059000000",
		"geoCountryId": "IT"
	},
	{
		"geoName": "Napoli",
		"domainNo": 1,
		"geoStateId": "NA",
		"geoCode": "NA",
		"geoCodeId": "039060000000",
		"geoCountryId": "IT"
	},
	{
		"geoName": "Novara",
		"domainNo": 1,
		"geoStateId": "NO",
		"geoCode": "NO",
		"geoCodeId": "039061000000",
		"geoCountryId": "IT"
	},
	{
		"geoName": "Nuoro",
		"domainNo": 1,
		"geoStateId": "NU",
		"geoCode": "NU",
		"geoCodeId": "039062000000",
		"geoCountryId": "IT"
	},
	{
		"geoName": "Ogliastra",
		"domainNo": 1,
		"geoStateId": "OG",
		"geoCode": "OG",
		"geoCodeId": "039063000000",
		"geoCountryId": "IT"
	},
	{
		"geoName": "Oristano",
		"domainNo": 1,
		"geoStateId": "OR",
		"geoCode": "OR",
		"geoCodeId": "039064000000",
		"geoCountryId": "IT"
	},
	{
		"geoName": "Olbia-Tempio",
		"domainNo": 1,
		"geoStateId": "OT",
		"geoCode": "OT",
		"geoCodeId": "039065000000",
		"geoCountryId": "IT"
	},
	{
		"geoName": "Palermo",
		"domainNo": 1,
		"geoStateId": "PA",
		"geoCode": "PA",
		"geoCodeId": "039066000000",
		"geoCountryId": "IT"
	},
	{
		"geoName": "Piacenza",
		"domainNo": 1,
		"geoStateId": "PC",
		"geoCode": "PC",
		"geoCodeId": "039067000000",
		"geoCountryId": "IT"
	},
	{
		"geoName": "Padova",
		"domainNo": 1,
		"geoStateId": "PD",
		"geoCode": "PD",
		"geoCodeId": "039068000000",
		"geoCountryId": "IT"
	},
	{
		"geoName": "Pescara",
		"domainNo": 1,
		"geoStateId": "PE",
		"geoCode": "PE",
		"geoCodeId": "039069000000",
		"geoCountryId": "IT"
	},
	{
		"geoName": "Perugia",
		"domainNo": 1,
		"geoStateId": "PG",
		"geoCode": "PG",
		"geoCodeId": "039070000000",
		"geoCountryId": "IT"
	},
	{
		"geoName": "Pisa",
		"domainNo": 1,
		"geoStateId": "PI",
		"geoCode": "PI",
		"geoCodeId": "039071000000",
		"geoCountryId": "IT"
	},
	{
		"geoName": "Pordenone",
		"domainNo": 1,
		"geoStateId": "PN",
		"geoCode": "PN",
		"geoCodeId": "039072000000",
		"geoCountryId": "IT"
	},
	{
		"geoName": "Prato",
		"domainNo": 1,
		"geoStateId": "PO",
		"geoCode": "PO",
		"geoCodeId": "039073000000",
		"geoCountryId": "IT"
	},
	{
		"geoName": "Parma",
		"domainNo": 1,
		"geoStateId": "PR",
		"geoCode": "PR",
		"geoCodeId": "039074000000",
		"geoCountryId": "IT"
	},
	{
		"geoName": "Pistoia",
		"domainNo": 1,
		"geoStateId": "PT",
		"geoCode": "PT",
		"geoCodeId": "039075000000",
		"geoCountryId": "IT"
	},
	{
		"geoName": "Pesaro-Urbino",
		"domainNo": 1,
		"geoStateId": "PU",
		"geoCode": "PU",
		"geoCodeId": "039076000000",
		"geoCountryId": "IT"
	},
	{
		"geoName": "Pavia",
		"domainNo": 1,
		"geoStateId": "PV",
		"geoCode": "PV",
		"geoCodeId": "039077000000",
		"geoCountryId": "IT"
	},
	{
		"geoName": "Potenza",
		"domainNo": 1,
		"geoStateId": "PZ",
		"geoCode": "PZ",
		"geoCodeId": "039078000000",
		"geoCountryId": "IT"
	},
	{
		"geoName": "Ravenna",
		"domainNo": 1,
		"geoStateId": "RA",
		"geoCode": "RA",
		"geoCodeId": "039079000000",
		"geoCountryId": "IT"
	},
	{
		"geoName": "Reggio di Calabria",
		"domainNo": 1,
		"geoStateId": "RC",
		"geoCode": "RC",
		"geoCodeId": "039080000000",
		"geoCountryId": "IT"
	},
	{
		"geoName": "Reggio nell'Emilia",
		"domainNo": 1,
		"geoStateId": "RE",
		"geoCode": "RE",
		"geoCodeId": "039081000000",
		"geoCountryId": "IT"
	},
	{
		"geoName": "Ragusa",
		"domainNo": 1,
		"geoStateId": "RG",
		"geoCode": "RG",
		"geoCodeId": "039082000000",
		"geoCountryId": "IT"
	},
	{
		"geoName": "Rieti",
		"domainNo": 1,
		"geoStateId": "RI",
		"geoCode": "RI",
		"geoCodeId": "039083000000",
		"geoCountryId": "IT"
	},
	{
		"geoName": "Roma",
		"domainNo": 1,
		"geoStateId": "RM",
		"geoCode": "RM",
		"geoCodeId": "039084000000",
		"geoCountryId": "IT"
	},
	{
		"geoName": "Rimini",
		"domainNo": 1,
		"geoStateId": "RN",
		"geoCode": "RN",
		"geoCodeId": "039085000000",
		"geoCountryId": "IT"
	},
	{
		"geoName": "Rovigo",
		"domainNo": 1,
		"geoStateId": "RO",
		"geoCode": "RO",
		"geoCodeId": "039086000000",
		"geoCountryId": "IT"
	},
	{
		"geoName": "Salerno",
		"domainNo": 1,
		"geoStateId": "SA",
		"geoCode": "SA",
		"geoCodeId": "039087000000",
		"geoCountryId": "IT"
	},
	{
		"geoName": "Siena",
		"domainNo": 1,
		"geoStateId": "SI",
		"geoCode": "SI",
		"geoCodeId": "039088000000",
		"geoCountryId": "IT"
	},
	{
		"geoName": "San Marino",
		"domainNo": 1,
		"geoStateId": "SM",
		"geoCode": "SM",
		"geoCodeId": "039089000000",
		"geoCountryId": "IT"
	},
	{
		"geoName": "Sondrio",
		"domainNo": 1,
		"geoStateId": "SO",
		"geoCode": "SO",
		"geoCodeId": "039090000000",
		"geoCountryId": "IT"
	},
	{
		"geoName": "La Spezia",
		"domainNo": 1,
		"geoStateId": "SP",
		"geoCode": "SP",
		"geoCodeId": "039091000000",
		"geoCountryId": "IT"
	},
	{
		"geoName": "Siracusa",
		"domainNo": 1,
		"geoStateId": "SR",
		"geoCode": "SR",
		"geoCodeId": "039092000000",
		"geoCountryId": "IT"
	},
	{
		"geoName": "Sassari",
		"domainNo": 1,
		"geoStateId": "SS",
		"geoCode": "SS",
		"geoCodeId": "039093000000",
		"geoCountryId": "IT"
	},
	{
		"geoName": "Savona",
		"domainNo": 1,
		"geoStateId": "SV",
		"geoCode": "SV",
		"geoCodeId": "039094000000",
		"geoCountryId": "IT"
	},
	{
		"geoName": "Taranto",
		"domainNo": 1,
		"geoStateId": "TA",
		"geoCode": "TA",
		"geoCodeId": "039095000000",
		"geoCountryId": "IT"
	},
	{
		"geoName": "Teramo",
		"domainNo": 1,
		"geoStateId": "TE",
		"geoCode": "TE",
		"geoCodeId": "039096000000",
		"geoCountryId": "IT"
	},
	{
		"geoName": "Trento",
		"domainNo": 1,
		"geoStateId": "TN",
		"geoCode": "TN",
		"geoCodeId": "039097000000",
		"geoCountryId": "IT"
	},
	{
		"geoName": "Torino",
		"domainNo": 1,
		"geoStateId": "TO",
		"geoCode": "TO",
		"geoCodeId": "039098000000",
		"geoCountryId": "IT"
	},
	{
		"geoName": "Trapani",
		"domainNo": 1,
		"geoStateId": "TP",
		"geoCode": "TP",
		"geoCodeId": "039099000000",
		"geoCountryId": "IT"
	},
	{
		"geoName": "Terni",
		"domainNo": 1,
		"geoStateId": "TR",
		"geoCode": "TR",
		"geoCodeId": "039100000000",
		"geoCountryId": "IT"
	},
	{
		"geoName": "Trieste",
		"domainNo": 1,
		"geoStateId": "TS",
		"geoCode": "TS",
		"geoCodeId": "039101000000",
		"geoCountryId": "IT"
	},
	{
		"geoName": "Treviso",
		"domainNo": 1,
		"geoStateId": "TV",
		"geoCode": "TV",
		"geoCodeId": "039102000000",
		"geoCountryId": "IT"
	},
	{
		"geoName": "Udine",
		"domainNo": 1,
		"geoStateId": "UD",
		"geoCode": "UD",
		"geoCodeId": "039103000000",
		"geoCountryId": "IT"
	},
	{
		"geoName": "Varese",
		"domainNo": 1,
		"geoStateId": "VA",
		"geoCode": "VA",
		"geoCodeId": "039104000000",
		"geoCountryId": "IT"
	},
	{
		"geoName": "Verbano-Cusio-Ossola",
		"domainNo": 1,
		"geoStateId": "VB",
		"geoCode": "VB",
		"geoCodeId": "039105000000",
		"geoCountryId": "IT"
	},
	{
		"geoName": "Vercelli",
		"domainNo": 1,
		"geoStateId": "VC",
		"geoCode": "VC",
		"geoCodeId": "039106000000",
		"geoCountryId": "IT"
	},
	{
		"geoName": "Venezia",
		"domainNo": 1,
		"geoStateId": "VE",
		"geoCode": "VE",
		"geoCodeId": "039107000000",
		"geoCountryId": "IT"
	},
	{
		"geoName": "Vicenza",
		"domainNo": 1,
		"geoStateId": "VI",
		"geoCode": "VI",
		"geoCodeId": "039108000000",
		"geoCountryId": "IT"
	},
	{
		"geoName": "Verona",
		"domainNo": 1,
		"geoStateId": "VR",
		"geoCode": "VR",
		"geoCodeId": "039109000000",
		"geoCountryId": "IT"
	},
	{
		"geoName": "Medio Campidano",
		"domainNo": 1,
		"geoStateId": "VS",
		"geoCode": "VS",
		"geoCodeId": "039110000000",
		"geoCountryId": "IT"
	},
	{
		"geoName": "Viterbo",
		"domainNo": 1,
		"geoStateId": "VT",
		"geoCode": "VT",
		"geoCodeId": "039111000000",
		"geoCountryId": "IT"
	},
	{
		"geoName": "Vibo Valentia",
		"domainNo": 1,
		"geoStateId": "VV",
		"geoCode": "VV",
		"geoCodeId": "039112000000",
		"geoCountryId": "IT"
	}
]